Metadata-Version: 2.1
Name: sideload_nu_0_bin_6633e71dacd3cb34a842096f
Version: 1.0.0
Summary: Sideloaded package
Author: Null Void
Requires-Python: >=3.8
